x_matrixlib/__init__.py
x_matrixlib/multiplier.py
x_matrixlib-0.1.dist-info/METADATA
x_matrixlib-0.1.dist-info/WHEEL
x_matrixlib-0.1.dist-info/top_level.txt
x_matrixlib-0.1.dist-info/RECORD
