Metadata-Version: 2.4
Name: x_matrixlib
Version: 0.1
Summary: A simple library to multiply matrices of different dimensions
Author: Primes
Dynamic: author
Dynamic: summary
